haskell_taboo_py/__init__.py
haskell_taboo_py/__main__.py
haskell_taboo_py-0.0.3.dist-info/licenses/LICENSE
haskell_taboo_py-0.0.3.dist-info/METADATA
haskell_taboo_py-0.0.3.dist-info/WHEEL
haskell_taboo_py-0.0.3.dist-info/entry_points.txt
haskell_taboo_py-0.0.3.dist-info/top_level.txt
haskell_taboo_py-0.0.3.dist-info/RECORD
