Metadata-Version: 2.4
Name: haskell-taboo-py
Version: 0.0.3
Summary: A banned identifiers checker for Haskell sources.
Author-email: Aly Cerruti <me@s5.pm>
License: MIT License
Project-URL: Homepage, https://github.com/UCSC-CSE-114A/taboo-checker-py
Project-URL: Repository, https://github.com/UCSC-CSE-114A/taboo-checker-py
Project-URL: Issues, https://github.com/UCSC-CSE-114A/taboo-checker-py/issues
Keywords: education
Classifier: Intended Audience :: Education
Classifier: License :: OSI Approved :: MIT License
Classifier: Programming Language :: Python :: 3.9
Requires-Python: >=3.9
License-File: LICENSE
Requires-Dist: click>=8.1.8
Requires-Dist: tree-sitter>=0.23.2
Requires-Dist: tree-sitter-haskell>=0.23.1
Provides-Extra: dev
Requires-Dist: build; extra == "dev"
Requires-Dist: setuptools>=75.3.2; extra == "dev"
Requires-Dist: packaging>=24.0; extra == "dev"
Requires-Dist: twine>=6.1; extra == "dev"
Requires-Dist: vermin; extra == "dev"
Dynamic: license-file
